timewreport/__init__.py
timewreport/config.py
timewreport/interval.py
timewreport/parser.py
timew_report-1.4.0.dist-info/LICENSE
timew_report-1.4.0.dist-info/METADATA
timew_report-1.4.0.dist-info/WHEEL
timew_report-1.4.0.dist-info/top_level.txt
timew_report-1.4.0.dist-info/RECORD
