Metadata-Version: 2.1
Name: timew-report
Version: 1.4.0
Summary: An interface for Timewarrior report data
Home-page: https://github.com/lauft/timew-report.git
Author: Thomas Lauf
Author-email: Thomas.Lauf@tngtech.com
License: MIT License
Project-URL: Bug Reports, https://github.com/lauft/timew-report/issues
Project-URL: Source, https://github.com/lauft/timew-report
Keywords: timewarrior taskwarrior time-tracking
Platform: UNKNOWN
Classifier: Development Status :: 5 - Production/Stable
Classifier: Intended Audience :: Developers
Classifier: Topic :: Utilities
Classifier: License :: OSI Approved :: MIT License
Classifier: Operating System :: OS Independent
Classifier: Programming Language :: Python :: 3
Classifier: Programming Language :: Python :: 3.7
Classifier: Programming Language :: Python :: 3.8
Classifier: Programming Language :: Python :: 3.9
Classifier: Programming Language :: Python :: 3 :: Only
Requires-Python: >3, <4
Requires-Dist: python-dateutil
Requires-Dist: deprecation
Provides-Extra: test
Requires-Dist: pytest ; extra == 'test'
